tradenity/__init__.py
tradenity/api_client.py
tradenity/configuration.py
tradenity/exceptions.py
tradenity/rest.py
tradenity/token_holder.py
tradenity/resources/__init__.py
tradenity/resources/address.py
tradenity/resources/braintree_gateway.py
tradenity/resources/brand.py
tradenity/resources/cancel_operation.py
tradenity/resources/cart_settings.py
tradenity/resources/cash_on_delivery_payment.py
tradenity/resources/category.py
tradenity/resources/collection.py
tradenity/resources/contact_info.py
tradenity/resources/countries_geo_zone.py
tradenity/resources/country.py
tradenity/resources/coupon.py
tradenity/resources/credit_card_payment.py
tradenity/resources/currency.py
tradenity/resources/customer.py
tradenity/resources/customer_group.py
tradenity/resources/dimensions.py
tradenity/resources/discount_coupon.py
tradenity/resources/discount_promotion.py
tradenity/resources/fixed_rate_shipping.py
tradenity/resources/free_item_coupon.py
tradenity/resources/free_shipping.py
tradenity/resources/free_shipping_coupon.py
tradenity/resources/free_shipping_promotion.py
tradenity/resources/gateway.py
tradenity/resources/general_settings.py
tradenity/resources/geo_zone.py
tradenity/resources/instance_meta.py
tradenity/resources/inventory_settings.py
tradenity/resources/items_selector.py
tradenity/resources/line_item.py
tradenity/resources/mail_server_settings.py
tradenity/resources/measurement_settings.py
tradenity/resources/option.py
tradenity/resources/option_set.py
tradenity/resources/option_value.py
tradenity/resources/order.py
tradenity/resources/order_line_item.py
tradenity/resources/paging.py
tradenity/resources/payment.py
tradenity/resources/payment_card.py
tradenity/resources/payment_settings.py
tradenity/resources/payment_source.py
tradenity/resources/payment_token.py
tradenity/resources/payment_transaction.py
tradenity/resources/photo.py
tradenity/resources/product.py
tradenity/resources/promotion.py
tradenity/resources/refund_operation.py
tradenity-1.0.1.dist-info/AUTHORS.rst
tradenity-1.0.1.dist-info/LICENSE
tradenity-1.0.1.dist-info/METADATA
tradenity-1.0.1.dist-info/WHEEL
tradenity-1.0.1.dist-info/top_level.txt
tradenity-1.0.1.dist-info/RECORD
