Metadata-Version: 2.1
Name: tradenity
Version: 1.0.1
Summary: Python SDK for the Tradenity e-commerce REST API
Home-page: https://github.com/tradenity/python-sdk
Author: Joseph Fouad
Author-email: tradenity@tradenity.com
License: APACHE
Platform: UNKNOWN
Classifier: Development Status :: 5 - Production/Stable
Classifier: Intended Audience :: Developers
Classifier: License :: OSI Approved :: Apache Software License
Classifier: Natural Language :: English
Classifier: Programming Language :: Python :: 2
Classifier: Programming Language :: Python :: 2.7
Requires-Dist: urllib3 (>=1.15)
Requires-Dist: six (>=1.10)
Requires-Dist: certifi
Requires-Dist: python-dateutil
